py_ocsf_models/__init__.py
py_ocsf_models/events/__init__.py
py_ocsf_models/events/base_event.py
py_ocsf_models/events/findings/__init__.py
py_ocsf_models/events/findings/activity_id.py
py_ocsf_models/events/findings/application_security_posture_finding.py
py_ocsf_models/events/findings/application_security_posture_finding_type_id.py
py_ocsf_models/events/findings/category_uid.py
py_ocsf_models/events/findings/class_uid.py
py_ocsf_models/events/findings/compliance_finding.py
py_ocsf_models/events/findings/compliance_finding_type_id.py
py_ocsf_models/events/findings/confidence_id.py
py_ocsf_models/events/findings/detection_finding.py
py_ocsf_models/events/findings/detection_finding_type_id.py
py_ocsf_models/events/findings/disposition_id.py
py_ocsf_models/events/findings/finding.py
py_ocsf_models/events/findings/impact_id.py
py_ocsf_models/events/findings/risk_level_id.py
py_ocsf_models/events/findings/severity_id.py
py_ocsf_models/events/findings/status_id.py
py_ocsf_models/objects/__init__.py
py_ocsf_models/objects/account.py
py_ocsf_models/objects/affected_software_package.py
py_ocsf_models/objects/analytic.py
py_ocsf_models/objects/api.py
py_ocsf_models/objects/assessment.py
py_ocsf_models/objects/check.py
py_ocsf_models/objects/cloud.py
py_ocsf_models/objects/compliance.py
py_ocsf_models/objects/compliance_status.py
py_ocsf_models/objects/container.py
py_ocsf_models/objects/cve.py
py_ocsf_models/objects/cvss.py
py_ocsf_models/objects/cwe.py
py_ocsf_models/objects/device.py
py_ocsf_models/objects/device_hardware_info.py
py_ocsf_models/objects/dns_query.py
py_ocsf_models/objects/enrichment.py
py_ocsf_models/objects/epss.py
py_ocsf_models/objects/evidence_artifacts.py
py_ocsf_models/objects/finding_info.py
py_ocsf_models/objects/fingerprint.py
py_ocsf_models/objects/geolocation.py
py_ocsf_models/objects/group.py
py_ocsf_models/objects/image.py
py_ocsf_models/objects/kb_article.py
py_ocsf_models/objects/kill_chain_phase.py
py_ocsf_models/objects/ldap_person.py
py_ocsf_models-0.8.0.dist-info/LICENSE
py_ocsf_models-0.8.0.dist-info/METADATA
py_ocsf_models-0.8.0.dist-info/WHEEL
py_ocsf_models-0.8.0.dist-info/RECORD
