Metadata-Version: 2.3
Name: py-ocsf-models
Version: 0.8.0
Summary: This is a Python implementation of the OCSF models. The models are used to represent the data of the OCSF Schema defined in https://schema.ocsf.io/.
License: Apache-2.0
Author: Prowler Engineering
Author-email: engineering@prowler.com
Requires-Python: >3.9.1,<3.15
Classifier: Programming Language :: Python :: 3
Classifier: License :: OSI Approved :: Apache Software License
Requires-Dist: cryptography (==44.0.1)
Requires-Dist: email-validator (==2.2.0)
Requires-Dist: pydantic (>=2.12.0,<3.0.0)
Project-URL: Changelog, https://github.com/prowler-cloud/py-ocsf-models/releases
Project-URL: Documentation, https://docs.prowler.cloud
Project-URL: Homepage, https://github.com/prowler-cloud/py-ocsf-models
Project-URL: Issue tracker, https://github.com/prowler-cloud/py-ocsf-models/issues
